arkhelm_tml/__init__.py
arkhelm_tml/arkhelm_tml.py
arkhelm_tml-0.0.3.dist-info/licenses/LICENSE
arkhelm_tml-0.0.3.dist-info/METADATA
arkhelm_tml-0.0.3.dist-info/WHEEL
arkhelm_tml-0.0.3.dist-info/top_level.txt
arkhelm_tml-0.0.3.dist-info/RECORD
